grid_graph.cpython-310-darwin.so
pygrid_graph.dylibs/libomp.dylib
pygrid_graph-0.0.4.dist-info/RECORD
pygrid_graph-0.0.4.dist-info/WHEEL
pygrid_graph-0.0.4.dist-info/top_level.txt
pygrid_graph-0.0.4.dist-info/METADATA
pygrid_graph-0.0.4.dist-info/licenses/LICENSE
