Metadata-Version: 2.4
Name: pygrid-graph
Version: 0.0.4
Summary: Some tools for manipulating nearest-neighbors graphs defined on regular grids
Author-email: Hugo Raguet <hugo.raguet@insa-cvl.fr>
Maintainer-email: Hugo Raguet <hugo.raguet@insa-cvl.fr>
License:                     GNU GENERAL PUBLIC LICENSE
Project-URL: homepage, https://gitlab.com/1a7r0ch3/grid-graph
Project-URL: repository, https://gitlab.com/1a7r0ch3/grid-graph.git
Keywords: graph,grid,nearest-neighbors,cut pursuit,graph signal processing
Classifier: Development Status :: 3 - Alpha
Classifier: Programming Language :: Python
Classifier: Topic :: Scientific/Engineering
Requires-Python: >=3.8
License-File: LICENSE
Dynamic: license-file
